dkpf/__init__.py
dkpf/cli.py
dkpf/commands.py
dkpf/config.py
dkpf/database.py
digikam_photo_finder-0.2.0.dist-info/entry_points.txt
digikam_photo_finder-0.2.0.dist-info/WHEEL
digikam_photo_finder-0.2.0.dist-info/METADATA
digikam_photo_finder-0.2.0.dist-info/RECORD
