Metadata-Version: 2.1
Name: digikam-photo-finder
Version: 0.2.0
Summary: 
Author: Andrew Halberstadt
Author-email: ahal@pm.me
Requires-Python: >=3.8,<4.0
Classifier: Programming Language :: Python :: 3
Classifier: Programming Language :: Python :: 3.8
Requires-Dist: appdirs (>=1.4.3,<2.0.0)
Requires-Dist: cleo (>=0.8.0,<0.9.0)
Requires-Dist: flake8 (>=3.7.9,<4.0.0)
Requires-Dist: loguru (>=0.4.1,<0.5.0)
Requires-Dist: tomlkit (>=0.5.11,<0.6.0)
